kid_duplex_controller.py
kid_protocol.py
kid_serial.py
kid_speech.py
kid_vision.py
xingkong_board.py
xingkong_board_data/__init__.py
xingkong_board_data/vosk-model-small-cn-0.22.zip
xingkong_board-2.0.2.dist-info/METADATA
xingkong_board-2.0.2.dist-info/WHEEL
xingkong_board-2.0.2.dist-info/top_level.txt
xingkong_board-2.0.2.dist-info/RECORD
