Metadata-Version: 2.4
Name: xingkong-board
Version: 2.0.2
Summary: 行空板双工通信与本地视觉控制库 - 支持手势识别、语音控制和传感器数据处理
Home-page: https://github.com/xingkong/xingkong-board
Author: XingKong Team
Author-email: xingkong@example.com
License: MIT
Keywords: xingkong board robot control vision speech gesture hardware education
Classifier: Development Status :: 4 - Beta
Classifier: Intended Audience :: Education
Classifier: Intended Audience :: Developers
Classifier: Topic :: Education
Classifier: Topic :: System :: Hardware
Classifier: Programming Language :: Python :: 3
Classifier: Programming Language :: Python :: 3.7
Classifier: Programming Language :: Python :: 3.8
Classifier: Programming Language :: Python :: 3.9
Classifier: Programming Language :: Python :: 3.10
Classifier: Programming Language :: Python :: 3.11
Classifier: License :: OSI Approved :: MIT License
Classifier: Operating System :: OS Independent
Requires-Python: >=3.7
Requires-Dist: pyserial>=3.5
Requires-Dist: opencv-python>=4.7.0
Requires-Dist: mediapipe>=0.10.0
Requires-Dist: pyttsx3>=2.90
Requires-Dist: vosk>=0.3.45
Requires-Dist: pyaudio>=0.2.13
Requires-Dist: SpeechRecognition>=3.10.0
Dynamic: author
Dynamic: author-email
Dynamic: classifier
Dynamic: description
Dynamic: description-content-type
Dynamic: home-page
Dynamic: keywords
Dynamic: license
Dynamic: requires-dist
Dynamic: requires-python
Dynamic: summary
